xontrib/pdb.py
xontrib/xog.py
xontrib_debug_tools-0.0.1.dist-info/LICENSE
xontrib_debug_tools-0.0.1.dist-info/METADATA
xontrib_debug_tools-0.0.1.dist-info/WHEEL
xontrib_debug_tools-0.0.1.dist-info/top_level.txt
xontrib_debug_tools-0.0.1.dist-info/RECORD
