Metadata-Version: 2.1
Name: xontrib-debug-tools
Version: 0.0.1
Summary: Debug tools for xonsh shell. 
Author-email: xontrib-debug-tools <no@no.no>
License: MIT License
Project-URL: Homepage, https://github.com/xonsh/xontrib-debug-tools
Project-URL: Documentation, https://github.com/xonsh/xontrib-debug-tools/blob/master/README.md
Project-URL: Code, https://github.com/xonsh/xontrib-debug-tools
Project-URL: Issue tracker, https://github.com/xonsh/xontrib-debug-tools/issues
Platform: any
Classifier: Programming Language :: Python :: 3
Classifier: License :: OSI Approved :: MIT License
Classifier: Operating System :: OS Independent
Classifier: Topic :: System :: Shells
Classifier: Topic :: System :: System Shells
Classifier: Topic :: Terminals
Requires-Python: >=3.8
License-File: LICENSE
Requires-Dist: xonsh (>=0.12.5)
Provides-Extra: dev
Requires-Dist: pytest (>=7.0) ; extra == 'dev'
